unit-tests/samples/sources/Counters.sv
// SPDX-FileCopyrightText: <text>Copyright 2024 Arm Limited and/or its
// affiliates <open-source-office@arm.com></text>
// SPDX-License-Identifier: Apache-2.0
//
// Licensed under the Apache License, Version 2.0 (the "License");
// you may not use this file except in compliance with the License.
// You may obtain a copy of the License at
//
//     http://www.apache.org/licenses/LICENSE-2.0
//
// Unless required by applicable law or agreed to in writing, software
// distributed under the License is distributed on an "AS IS" BASIS,
// WITHOUT WARRANTIES OR CONDITIONS OF ANY KIND, either express or implied.
// See the License for the specific language governing permissions and
// limitations under the License.
//
// This file is part of PAF, the Physical Attack Framework.

// Simple counter with its testbench. Used to provide test data.
//
// Compile with:
//   iverilog -o Counters Counters.v
//
// Run with:
//   Counters -fst
//
// Et voilà, you now have a fst file that can be used for testing.

`timescale 1 ns / 1 ps

// =========================================================================
// Test bench
// -------------------------------------------------------------------------
module counters(clk, reset, cnt1, cnt2);

input clk;
input reset;
output [7:0] cnt1;
reg [8:0] cnt;
output integer cnt2;

assign cnt1 = cnt[8:1];

always @(negedge reset or posedge clk)
begin
  if(reset == 1'b0)
  begin
    cnt = 0;
    cnt2 = 0;
  end
  else
  begin
    cnt = cnt + 1;
    cnt2 = cnt2 + 1;
  end
end
endmodule

// =========================================================================
// Test bench
// -------------------------------------------------------------------------
module tbench;

reg clk;
reg reset;
wire [7:0] cnt1;
wire integer cnt2;

initial
begin
  $dumpfile("Counters.waves");
  $dumpvars(0, tbench);
  clk = 1'b1;
  reset = 1'b0;
  repeat(2) #5 clk = ~clk;
  reset = 1'b1;
  repeat(20) #5 clk = ~clk;
  $finish(0);
end

counters DUT(
  .clk(clk),
  .reset(reset),
  .cnt1(cnt1),
  .cnt2(cnt2)
);

endmodule

unit-tests/samples/Counters.vcd
$date
	Wed Mar 27 20:29:54 2024
$end
$version
	Icarus Verilog
$end
$timescale
	1ps
$end
$scope module tbench $end
$var wire 32 ! cnt2 [31:0] $end
$var wire 8 " cnt1 [7:0] $end
$var reg 1 # clk $end
$var reg 1 $ reset $end
$scope module DUT $end
$var wire 1 # clk $end
$var wire 1 $ reset $end
$var wire 8 % cnt1 [7:0] $end
$var reg 9 & cnt [8:0] $end
$var integer 32 ' cnt2 [31:0] $end
$upscope $end
$upscope $end
$enddefinitions $end
$comment Show the parameter values. $end
$dumpall
$end
#0
$dumpvars
b0 '
b0 &
b0 %
0$
1#
b0 "
b0 !
$end
#5000
0#
#10000
b1 !
b1 '
b1 &
1$
1#
#15000
0#
#20000
b1 "
b1 %
b10 !
b10 '
b10 &
1#
#25000
0#
#30000
b11 !
b11 '
b11 &
1#
#35000
0#
#40000
b10 "
b10 %
b100 !
b100 '
b100 &
1#
#45000
0#
#50000
b101 !
b101 '
b101 &
1#
#55000
0#
#60000
b11 "
b11 %
b110 !
b110 '
b110 &
1#
#65000
0#
#70000
b111 !
b111 '
b111 &
1#
#75000
0#
#80000
b100 "
b100 %
b1000 !
b1000 '
b1000 &
1#
#85000
0#
#90000
b1001 !
b1001 '
b1001 &
1#
#95000
0#
#100000
b101 "
b101 %
b1010 !
b1010 '
b1010 &
1#
#105000
0#
#110000
b1011 !
b1011 '
b1011 &
1#
